filters/__init__.py
filters/filters_t.hdf5
filters/filters_w.hdf5
piXedfit/__init__.py
piXedfit/__init__.pyc
piXedfit/__pycache__/__init__.cpython-35.pyc
piXedfit/__pycache__/filtering.cpython-35.pyc
piXedfit/__pycache__/igm_absorption.cpython-35.pyc
piXedfit/__pycache__/piXedfit_analysis.cpython-35.pyc
piXedfit/__pycache__/piXedfit_bin.cpython-35.pyc
piXedfit/__pycache__/piXedfit_fitting.cpython-35.pyc
piXedfit/__pycache__/piXedfit_images.cpython-35.pyc
piXedfit/__pycache__/piXedfit_model.cpython-35.pyc
piXedfit/__pycache__/piXedfit_spectrophotometric.cpython-35.pyc
piXedfit/__pycache__/posteriors.cpython-35.pyc
piXedfit/__pycache__/redshifting.cpython-35.pyc
piXedfit/piXedfit_analysis/__init__.py
piXedfit/piXedfit_analysis/__init__.pyc
piXedfit/piXedfit_analysis/plotting.py
piXedfit/piXedfit_analysis/plotting.pyc
piXedfit/piXedfit_analysis/__pycache__/__init__.cpython-35.pyc
piXedfit/piXedfit_analysis/__pycache__/plotting.cpython-35.pyc
piXedfit/piXedfit_bin/__init__.py
piXedfit/piXedfit_bin/__init__.pyc
piXedfit/piXedfit_bin/pixbin.py
piXedfit/piXedfit_bin/__pycache__/__init__.cpython-35.pyc
piXedfit/piXedfit_bin/__pycache__/photo_bin.cpython-35.pyc
piXedfit/piXedfit_bin/__pycache__/pixbin.cpython-35.pyc
piXedfit/piXedfit_bin/__pycache__/specphoto_bin.cpython-35.pyc
piXedfit/piXedfit_fitting/__init__.py
piXedfit/piXedfit_fitting/__init__.pyc
piXedfit/piXedfit_fitting/fitting.py
piXedfit/piXedfit_fitting/fitting.pyc
piXedfit/piXedfit_fitting/fitutils.py
piXedfit/piXedfit_fitting/mc_nsmp_p2.py
piXedfit/piXedfit_fitting/mc_nsmp_p2_sp.py
piXedfit/piXedfit_fitting/mc_p1.py
piXedfit/piXedfit_fitting/mc_p1_sp.py
piXedfit/piXedfit_fitting/mc_p2.py
piXedfit/piXedfit_fitting/mc_p2_sp.py
piXedfit/piXedfit_fitting/rd_fz.py
piXedfit/piXedfit_fitting/rd_fz_blk.py
piXedfit/piXedfit_fitting/rd_fz_nsmp.py
piXedfit/piXedfit_fitting/rd_fz_nsmp_blk.py
piXedfit/piXedfit_fitting/rd_fz_nsmp_sp.py
piXedfit/piXedfit_fitting/rd_fz_sp.py
piXedfit/piXedfit_fitting/rd_vz.py
pixedfit-1.0.dist-info/LICENSE.txt
pixedfit-1.0.dist-info/METADATA
pixedfit-1.0.dist-info/WHEEL
pixedfit-1.0.dist-info/top_level.txt
pixedfit-1.0.dist-info/RECORD
