Metadata-Version: 2.1
Name: pixedfit
Version: 1.0
Summary: A python package specially designed for SED fitting of resolved sources
Home-page: UNKNOWN
Author: Abdurrouf
Author-email: fabdurr1@jhu.edu
License: MIT
Project-URL: Documentation, https://pixedfit.readthedocs.io
Project-URL: Source repo, https://github.com/aabdurrouf/piXedfit
Platform: UNKNOWN
Classifier: Development Status :: 4 - Beta
Classifier: Intended Audience :: Science/Research
Classifier: Programming Language :: Python :: 3
Classifier: License :: OSI Approved :: MIT License
Classifier: Natural Language :: English
Classifier: Topic :: Scientific/Engineering :: Astronomy
Requires-Python: >=3.7, <4
Requires-Dist: numpy
Requires-Dist: h5py
Requires-Dist: scipy
Requires-Dist: astropy
Requires-Dist: photutils (==1.1.0)
Requires-Dist: matplotlib
Requires-Dist: reproject (>=0.7)
Requires-Dist: sep
Requires-Dist: emcee
Requires-Dist: schwimmbad
Requires-Dist: astroquery
Requires-Dist: pyvo
Requires-Dist: pandas
Requires-Dist: tqdm
